LICENSE
MANIFEST.in
README.md
pyproject.toml
setup.cfg
setup.py
fast_csv_middleware.egg-info/PKG-INFO
fast_csv_middleware.egg-info/SOURCES.txt
fast_csv_middleware.egg-info/dependency_links.txt
fast_csv_middleware.egg-info/requires.txt
fast_csv_middleware.egg-info/top_level.txt
fastapicsv/__init__.py
fastapicsv/example.py
fastapicsv/middlewares.py
venv/lib/python3.12/site-packages/typing_extensions.py
venv/lib/python3.12/site-packages/annotated_types/__init__.py
venv/lib/python3.12/site-packages/annotated_types/test_cases.py
venv/lib/python3.12/site-packages/anyio/__init__.py
venv/lib/python3.12/site-packages/anyio/from_thread.py
venv/lib/python3.12/site-packages/anyio/lowlevel.py
venv/lib/python3.12/site-packages/anyio/pytest_plugin.py
venv/lib/python3.12/site-packages/anyio/to_process.py
venv/lib/python3.12/site-packages/anyio/to_thread.py
venv/lib/python3.12/site-packages/anyio-4.2.0.dist-info/entry_points.txt
venv/lib/python3.12/site-packages/anyio-4.2.0.dist-info/top_level.txt
venv/lib/python3.12/site-packages/anyio/_backends/__init__.py
venv/lib/python3.12/site-packages/anyio/_backends/_asyncio.py
venv/lib/python3.12/site-packages/anyio/_backends/_trio.py
venv/lib/python3.12/site-packages/anyio/_core/__init__.py
venv/lib/python3.12/site-packages/anyio/_core/_eventloop.py
venv/lib/python3.12/site-packages/anyio/_core/_exceptions.py
venv/lib/python3.12/site-packages/anyio/_core/_fileio.py
venv/lib/python3.12/site-packages/anyio/_core/_resources.py
venv/lib/python3.12/site-packages/anyio/_core/_signals.py
venv/lib/python3.12/site-packages/anyio/_core/_sockets.py
venv/lib/python3.12/site-packages/anyio/_core/_streams.py
venv/lib/python3.12/site-packages/anyio/_core/_subprocesses.py
venv/lib/python3.12/site-packages/anyio/_core/_synchronization.py
venv/lib/python3.12/site-packages/anyio/_core/_tasks.py
venv/lib/python3.12/site-packages/anyio/_core/_testing.py
venv/lib/python3.12/site-packages/anyio/_core/_typedattr.py
venv/lib/python3.12/site-packages/anyio/abc/__init__.py
venv/lib/python3.12/site-packages/anyio/abc/_eventloop.py
venv/lib/python3.12/site-packages/anyio/abc/_resources.py
venv/lib/python3.12/site-packages/anyio/abc/_sockets.py
venv/lib/python3.12/site-packages/anyio/abc/_streams.py
venv/lib/python3.12/site-packages/anyio/abc/_subprocesses.py
venv/lib/python3.12/site-packages/anyio/abc/_tasks.py
venv/lib/python3.12/site-packages/pip-23.2.1.dist-info/AUTHORS.txt
venv/lib/python3.12/site-packages/pip-23.2.1.dist-info/LICENSE.txt
venv/lib/python3.12/site-packages/pip-23.2.1.dist-info/entry_points.txt
venv/lib/python3.12/site-packages/pip-23.2.1.dist-info/top_level.txt
venv/lib/python3.12/site-packages/sniffio-1.3.0.dist-info/top_level.txt
