Metadata-Version: 2.1
Name: fast-csv-middleware
Version: 0.1.3
Summary: A CSV Middleware for FastAPI
Home-page: https://github.com/mahyess/fastapicsv
Author: Mahesh Prajapati
Author-email: Mahesh Prajapati <zephyrr2722@gmail.com>
License: Copyright 2024 Mahesh Prajapati
Project-URL: homepage, https://github.com/mahyess/fastapicsv
Keywords: fastapi,csv,middleware
Classifier: License :: OSI Approved :: BSD License
Classifier: Programming Language :: Python
Classifier: Programming Language :: Python :: 3
Requires-Python: >=3.8
License-File: LICENSE
Requires-Dist: fastapi
